{"cameraMode":{"drawMode":0,"name":"Shaded","section":"Shading Mode"},"sceneLighting":true,"audioPlay":true,"sceneViewState":{"m_AlwaysRefresh":true,"showFog":true,"showSkybox":false,"showFlares":true,"showImageEffects":true,"showParticleSystems":true,"showVisualEffectGraphs":true,"m_FxEnabled":true},"in2DMode":false,"pivot":{"x":0.0,"y":-0.13170886039733888,"z":0.0},"rotation":{"x":0.32173237204551699,"y":0.18803083896636964,"z":-0.0653495341539383,"w":0.9256858825683594},"size":1.659496784210205,"orthographic":false}